.dockerignore
Dockerfile
TROUBLESHOOTING.md
docker-compose.yml
vectory/__init__.py
vectory/cli.py
vectory/datasets.py
vectory/db/bulk.py
vectory/db/models.py
vectory/demo.py
vectory/es/api.py
vectory/es/client.py
vectory/es/docker.py
vectory/es/utils.py
vectory/exceptions.py
vectory/experiments.py
vectory/indices.py
vectory/spaces.py
vectory/utils.py
vectory/visualization/main.py
vectory/visualization/run.py
vectory/visualization/utils.py
vectory-0.1.7.dist-info/entry_points.txt
vectory-0.1.7.dist-info/WHEEL
vectory-0.1.7.dist-info/METADATA
vectory-0.1.7.dist-info/RECORD
