Metadata-Version: 2.1
Name: vectory
Version: 0.1.7
Summary: Streamline the benchmark and experimentation process of your models that rely on generating embeddings
Home-page: https://github.com/pentoai/vectory
License: MIT
Keywords: machine-learning,embeddings,visualization,feature similarity,feature store
Author: Pento
Author-email: hello@pento.ai
Requires-Python: >=3.7.1,<3.11
Classifier: Development Status :: 3 - Alpha
Classifier: Intended Audience :: Developers
Classifier: Intended Audience :: Education
Classifier: Intended Audience :: Science/Research
Classifier: License :: OSI Approved :: MIT License
Classifier: Natural Language :: English
Classifier: Programming Language :: Python
Classifier: Programming Language :: Python :: 3
Classifier: Programming Language :: Python :: 3.8
Classifier: Programming Language :: Python :: 3.9
Classifier: Programming Language :: Python :: 3.10
Classifier: Programming Language :: Python :: 3.10
Classifier: Programming Language :: Python :: 3.7
Classifier: Programming Language :: Python :: 3.8
Classifier: Programming Language :: Python :: 3.9
Classifier: Topic :: Scientific/Engineering :: Mathematics
Classifier: Topic :: Scientific/Engineering :: Visualization
Classifier: Topic :: Software Development :: Libraries
Classifier: Topic :: Software Development :: Libraries :: Python Modules
Requires-Dist: Jinja2 (==3.0.1)
Requires-Dist: Pillow (>=9.2.0,<10.0.0)
Requires-Dist: bokeh (<=2.2.3)
Requires-Dist: coolname (>=1.1.0,<2.0.0)
Requires-Dist: docker-compose (>=1.29.2,<2.0.0)
Requires-Dist: elasticsearch (==7.16.3)
Requires-Dist: elasticsearch-dsl (>=7.0.0,<8.0.0)
Requires-Dist: matplotlib (>=3.3)
Requires-Dist: numpy (>=1.14.5)
Requires-Dist: pandas (>=1.3.5,<2.0.0)
Requires-Dist: peewee (>=3.14.10,<4.0.0)
Requires-Dist: plotly (>=5.9.0,<6.0.0)
Requires-Dist: psutil (>=5.9.1,<6.0.0)
Requires-Dist: pynndescent (>=0.5.6,<0.6.0)
Requires-Dist: streamlit (>=1.8.1,<1.12.0)
Requires-Dist: streamlit-bokeh-events (>=0.1.2,<0.2.0)
Requires-Dist: tabulate (>=0.8.10,<0.9.0)
Requires-Dist: tqdm (>=4.61.1,<5.0.0)
Requires-Dist: typer (>=0.4.0,<0.5.0)
Requires-Dist: umap-learn (>=0.5.3,<0.6.0)
Project-URL: Repository, https://github.com/pentoai/vectory
